LICENSE
MANIFEST.in
README.md
setup.py
webz/__init__.py
webz/base.py
webz/config.py
webz/configz.py
webz.egg-info/PKG-INFO
webz.egg-info/SOURCES.txt
webz.egg-info/dependency_links.txt
webz.egg-info/top_level.txt
webz/css/bootstrap/bootstrap.min.css
webz/demo/run.py
webz/demo/runz.py
webz/demo/test.confz
webz/demo/test.js
webz/demo/testz.js
webz/demo/pages/test.html
webz/demo/pages/test1.html
webz/demo/pages/test2.html
webz/demo/pages/testComp.html
webz/demo/servers/test.py
webz/js/base.js
webz/js/packs.js
webz/js/utils.js
webz/js/utils_img.js
webz/js/bootstrap/bootstrap.bundle.min.js
webz/js/clipboard/clipboard.min.js
webz/js/jquery/jquery.min.js
webz/js/vue/vue.min.js
webz/profiles/base.confz