Metadata-Version: 2.1
Name: webz
Version: 0.0.9
Summary: 简单的web服务器框架，实现的是配置文件的读取和调用，内部调用web.py
Home-page: https://github.com/buildCodeZ/webz
Author: Zzz
Author-email: 1309458652@qq.com
License: MIT License
Keywords: webz
Platform: any
License-File: LICENSE
